{
    "time": "10h00",
    "date": "24/04/2018",
    "title": "Chuta, Pimpão! Atacante do Botafogo repete gol perdido de 2017 e irrita torcida.Cara a cara com o goleiro, camisa 7 alvinegro toma decisão equivocada diante do Sport e perde gol feito em lance parecido com o que teve contra o Santos, no Campeonato Brasileiro do ano passado",
    "author": "GloboEsporte.com",
    "text": [
        "Início de jogo, Pimpão pressiona a marcação. Rouba a bola, avança em velocidade e sai cara a cara com o goleiro adversário. Mas tenta procurar um companheiro ao lado para dar o passe, se atrapalha e perde o gol feito. A descrição é do lance em que o camisa 7 do Botafogo teve logo aos quatro minutos de jogo no empate por 1 a 1 com o Sport, na Ilha do Retiro, na noite de segunda-feira, pela segunda rodada do Campeonato Brasileiro.",
        "Mas ela também pode ser usada para narrar outro lance da Série A do ano passado: na derrota por 1 a 0 para o Santos no Pacaembu, pela quinta rodada, quando o atacante teve a chance clara aos 14 minutos do primeiro tempo. Em comum, o fato de ambas as jogadas terem sido fora de casa e custado caro, com o time sofrendo gol e ficando atrás do placar. Além do grito uníssono da torcida alvinegra pelo Brasil: Chuta, Pimpão!",
        "",
        "",
        "",
        "Em entrevista coletiva após a partida desta segunda, Valentim minimizou o lance e jogou a responsabilidade para o gramado da Ilha do Retiro, castigado pelas chuvas em Recife.",
        "– O campo fez com que o Pimpão não conseguisse levar a bola em velocidade, mas antes do Pimpão teve um erro do Sport por causa do campo e não por falta de qualidade ou um erro técnico do jogador – ponderou o treinador, evitando responsabilizar o atacante.",
        "Mas a revolta com ele nas redes sociais foi tanta, que Pimpão virou meme e entrou no Trending Topics do Twitter – assuntos mais comentados no Brasil – durante a noite.",
        "",
        "TUA ESTRELA SOLITÁRIA NOS CONDUZ... FAÇA PARTE: CLIQUE AQUI!"
    ],
    "comments": [
        {
            "name": "Alexandre Rocha",
            "text": "O jogador de tão criticado,perde a confiança.ele tem contrato com o clube então devemos ajudá-lo a melhorar !",
            "date": "2018-04-24T21:47:12",
            "likes": "17",
            "unlikes": "4",
            "replies": [
                {
                    "name": "Claudio Batista",
                    "text": "Ele treina a semana inteira....me ajuda ai !!!!",
                    "date": "2018-04-25T10:24:49",
                    "likes": "4",
                    "unlikes": "0"
                },
                {
                    "name": "José Barros",
                    "text": "Pimpão tem crédito.",
                    "date": "2018-04-25T20:42:03",
                    "likes": "1",
                    "unlikes": "1"
                }
            ],
            "n_replies": 2
        },
        {
            "name": "Josue Martins",
            "text": "BRASILEIRO É TUDO IDIOTA. O BARCELONA TOMOU DE TRÊS FOI ELIMINADO,E VC NÃO VÊ TORCEDOR RESMUNGANDO NA INTERNET,PELO CONTRÁRIO, TODO JOGO CASA CHEIA PARA ASSISTIR O TIME E AJUDAR ARRECADAR DINHEIRO PARA COMPRAR BONS JOGADORES. ESSA É A DIFERENÇA A CULTURA DOS EUROPEUS. AINDA DIZEM QUE BRASILEIRO AMA FUTEBOL. NEM AQUI NEM NA CHINA.",
            "date": "2018-04-24T12:23:52",
            "likes": "41",
            "unlikes": "23",
            "replies": [
                {
                    "name": "Celso Rosa",
                    "text": "Você quer comparar o Pimpão com quem do Barcelona?",
                    "date": "2018-04-24T12:57:26",
                    "likes": "18",
                    "unlikes": "5"
                },
                {
                    "name": "Jorge Pimenta",
                    "text": "O que vc falou e vdd mas tbem todo ano o Barcelona ganha algum título, essa é a diferença, lembrando que o Botafogo não foi pra libertadores por um ponto este ano por aí vc vê como fez falta é-se golzinho né",
                    "date": "2018-04-24T13:00:41",
                    "likes": "17",
                    "unlikes": "0"
                },
                {
                    "name": "Fernando Rocha",
                    "text": "To cheio dessa torcida que só elogia quanto ganha pqpr",
                    "date": "2018-04-24T13:26:20",
                    "likes": "6",
                    "unlikes": "11"
                },
                {
                    "name": "Isis Valdeci",
                    "text": "A gente quase nunca elogia pq o botafogo não ganha quase nada",
                    "date": "2018-04-24T13:48:55",
                    "likes": "17",
                    "unlikes": "6"
                },
                {
                    "name": "Joao Branco",
                    "text": "Fernando Rocha ! você já viu alguém elogiar outro alguém por ter feito um montedekagada ou por não fazer nada certo ?",
                    "date": "2018-04-24T14:24:43",
                    "likes": "9",
                    "unlikes": "2"
                },
                {
                    "name": "Jose Menezes",
                    "text": "Pô comparar esse time com o Barcelona? Acorda Zé ruela.",
                    "date": "2018-04-24T15:39:15",
                    "likes": "7",
                    "unlikes": "4"
                },
                {
                    "name": "José Calegario",
                    "text": "Todo torcedor brasileiro, principalmente os cariocas, tem mania de vaiar seu time por qualquer coisa. Isso prejudica muito.",
                    "date": "2018-04-24T16:00:01",
                    "likes": "9",
                    "unlikes": "3"
                },
                {
                    "name": "Paulo Oliveira",
                    "text": "O Josué fumou alguma coisa estragada! O torcedor do Barcelona reclama de que, Josué? Ganharam tudo !",
                    "date": "2018-04-24T18:40:20",
                    "likes": "5",
                    "unlikes": "1"
                },
                {
                    "name": "Ravi Giudice",
                    "text": "O Barcelona não tem um pimpão !",
                    "date": "2018-04-24T19:00:47",
                    "likes": "9",
                    "unlikes": "1"
                },
                {
                    "name": "Danilo Oliveira",
                    "text": "Desde 95 não ganha um título de expressão. Muitos que estão escrevendo aqui na página são jovens e só presenciaram títulos do carioca... Além disso o Botafogo não venceu 1 libertadores isso é uma vergonha",
                    "date": "2018-04-24T20:41:34",
                    "likes": "8",
                    "unlikes": "2"
                },
                {
                    "name": "Giovani Souza",
                    "text": "Danilo e se a torcida não lotar os estádios nunca vai ganhar, tem torcedor que espera um milagre pro Botafogo se levantar, só a torcida pode erguer o clube.",
                    "date": "2018-04-24T22:05:35",
                    "likes": "1",
                    "unlikes": "0"
                },
                {
                    "name": "Claudio Batista",
                    "text": "Concordo Danilo.... Nao aguento mais Carioca e titulo de expressao que eh bom NADA... Ano passado se nao fosse o covarde do Jair Ventura teriamos conquistado a Copa do Brasil e a Libertadores...",
                    "date": "2018-04-25T10:21:40",
                    "likes": "2",
                    "unlikes": "0"
                }
            ],
            "n_replies": 12
        },
        {
            "name": "Wandersonpaulodeoliveirafelisberto",
            "text": "Pimpão somos muitos gratos pela libertadores que você fez ano passado agora JÁ tem um bom tempo que você nao faz nem 1% daquelas maravilhosas atuações diretoria é só olhar e ver tem jogadores que JÁ NÃO podem acrescentar nada de bom ao nosso glorioso são eles l.ricardo d.cearense pimpão valência Gilson espero que ano que vem ou vocês os usem como moeda de troca ou simplesmente os descartem pois JÁ seriam uma grande ajuda vocês fazerem isso fui",
            "date": "2018-04-24T11:00:40",
            "likes": "65",
            "unlikes": "8",
            "replies": [
                {
                    "name": "Edinaldo Santos",
                    "text": "Valentim, toda vez que vc escalar leo Valencia eu varios torcedor nao vamos mais assistir o jogo. mim diga mais uma vez de quer posição ele joga pelo amor de Deus.",
                    "date": "2018-04-24T11:17:26",
                    "likes": "8",
                    "unlikes": "8"
                },
                {
                    "name": "Tiago",
                    "text": "Mesmo sendo prata da casa, incluiria o Marcinho. Não sabe defender, não sabe atacar, não sabe cruzar, perder todas as bolas divididas. Jogador Nutella",
                    "date": "2018-04-24T11:26:32",
                    "likes": "21",
                    "unlikes": "9"
                },
                {
                    "name": "Edson Braz",
                    "text": "Edinaldo, faço parte dos que não irão assistir está merdajogar.",
                    "date": "2018-04-24T11:45:55",
                    "likes": "1",
                    "unlikes": "3"
                },
                {
                    "name": "Claudio Batista",
                    "text": "Wanderson, vc deve estar de brincadeira ne ??? Agradecer ao Pimpao pela Libertadores do ano passado, pq ? Fomos campeoes ??? Esse cara que vc aplaude no jogo de volta contra o gremio na Libertadores fez o inverso de ontem, ele foi fominha e nao deu o passe para o JPaulo fazer o gol quando ainda estava 0x0.... Sabe pq isso ??Pq ele ja tinha igualado ao Jairzinho em gols na Libertadores, quis ficar na frente e deu no que deu...fomos eliminados numa competicao que fizemos uma campanha linda e que podiamos ter levado esse caneco inedito....",
                    "date": "2018-04-24T12:15:28",
                    "likes": "12",
                    "unlikes": "3"
                },
                {
                    "name": "Anndersson Pereira",
                    "text": "A culpa foi do Jair Ventura que foi covarde e colocou o fogão para jogar igual time pequeno , quando deveria enfrentar o Grêmio de igual pra igual , pois o empate com gols nos favorecia .",
                    "date": "2018-04-25T00:42:36",
                    "likes": "3",
                    "unlikes": "0"
                },
                {
                    "name": "Miguel Moreira",
                    "text": "Pimpão é um jogador sem recursos e sem personalidade e o pior: é muito violento. Por falta de recursos, toma cartão em todos os jogos, deixando o time vulnerável, fazendo com que o técnico seja obrigado a substituí-lo.",
                    "date": "2018-04-25T07:42:23",
                    "likes": "6",
                    "unlikes": "0"
                },
                {
                    "name": "Claudio Batista",
                    "text": "Anderson...Jair foi covarde nesse jogo e contra os mu lam bos na Copa do Brasil....",
                    "date": "2018-04-25T10:19:47",
                    "likes": "4",
                    "unlikes": "0"
                }
            ],
            "n_replies": 7
        },
        {
            "name": "Anndersson Pereira",
            "text": "J",
            "date": "2018-04-25T00:32:03",
            "likes": "1",
            "unlikes": "0",
            "replies": [],
            "n_replies": 0
        },
        {
            "name": "Marco Perez",
            "text": "O Pimpão era um atacante veloz, agudo e driblador, que partia para cima dos atacantes e resolvia. Quem matou esse atacante foi o Jair Ventura, com a obsessão em fazê-lo voltar para ajudar o nosso lateral na marcação. Essa mania em marcar e dar carrinhos descontrolados, acabaram com aquele bom atacante que tínhamos. Agradeçam ao retranqueiro JV.",
            "date": "2018-04-24T22:44:59",
            "likes": "15",
            "unlikes": "2",
            "replies": [],
            "n_replies": 0
        },
        {
            "name": "Otávio Castro",
            "text": "Pimpão já deu. Pode começar a preparar o consultório pq o Botafogo vai ser o ultimo grande clube em que ele vai jogar. É daí pra baixo. Depois, é voltar pro consultório e virar dentista de novo.",
            "date": "2018-04-24T10:55:28",
            "likes": "33",
            "unlikes": "6",
            "replies": [
                {
                    "name": "Paulo Santos",
                    "text": "Ele não concluiu o curso de odontologia, tem uma matéria falando sobre isso.",
                    "date": "2018-04-24T16:16:04",
                    "likes": "2",
                    "unlikes": "0"
                },
                {
                    "name": "Jose Cani",
                    "text": "com esse time o gatito vai se consagrar e se tornar o melhor goleiro do mundo. marcinho, gilson avenida, lindoso, valencia, pimpão, ezequiel, pachu, dudu cearense, bochecha. é sofrimento demais. pior de tudo é essas pragas serem titulares. fora ALBERTO VALENTIM. Perto dessas porcarias e Marcos Vinicius doente, cheio de asma, é melhor que todos esses.",
                    "date": "2018-04-24T17:43:12",
                    "likes": "5",
                    "unlikes": "5"
                },
                {
                    "name": "Jose Cani",
                    "text": "FORA ALBERTO VALENTIM, FORA PIMPÃO, FORA LINDOSO, FORA EZEQUIEL, FORA PACHU, FORA GILSON, FORA MARCINHO. DEUS OLHAI POR NÓS.",
                    "date": "2018-04-24T17:45:02",
                    "likes": "4",
                    "unlikes": "13"
                },
                {
                    "name": "Vinicius Osbourne",
                    "text": "alberto nao tem culpa culpado disso foi pimpão",
                    "date": "2018-04-24T21:50:29",
                    "likes": "3",
                    "unlikes": "0"
                },
                {
                    "name": "Vinicius Osbourne",
                    "text": "pimpao ta ruim mesmo esse ano nao ta jogando nada",
                    "date": "2018-04-24T21:51:16",
                    "likes": "3",
                    "unlikes": "0"
                }
            ],
            "n_replies": 5
        },
        {
            "name": "Thiago Machado",
            "text": "Fez igual com contra o Santos ano passado parece replay.... Jogador sem confiança é assim mesmo",
            "date": "2018-04-24T21:29:40",
            "likes": "2",
            "unlikes": "0",
            "replies": [],
            "n_replies": 0
        },
        {
            "name": "Jose Cani",
            "text": "time que tem titulares pimpão e valencia, que quando saem, entram pachu e ezequiel, vai jogar pra não cair, e olhe lá. que coisa horrivel. será que esse treinador não tá de sacanagem????",
            "date": "2018-04-24T17:35:24",
            "likes": "7",
            "unlikes": "5",
            "replies": [
                {
                    "name": "Gilson Appolonio",
                    "text": "bochecha,, pachu ,,gilson,,marcinho com essa turma vai brigar para não cair",
                    "date": "2018-04-24T21:23:35",
                    "likes": "5",
                    "unlikes": "0"
                }
            ],
            "n_replies": 1
        },
        {
            "name": "Guilherme Ferreira",
            "text": "Jogador COVARDE E MEFIOCRE",
            "date": "2018-04-24T21:04:45",
            "likes": "7",
            "unlikes": "0",
            "replies": [],
            "n_replies": 0
        },
        {
            "name": "Danilo Oliveira",
            "text": "Acrescente o gol perdido contra o Flamenguinho em 2016. A partida terminou 0x0",
            "date": "2018-04-24T20:36:26",
            "likes": "10",
            "unlikes": "0",
            "replies": [],
            "n_replies": 0
        },
        {
            "name": "Ullysses Ribeiro",
            "text": "Pimpão ta sem a confiança, treinador tem que conversar com ele e tentar recupera-lo pq precisamos muito dele, tá muito tenso pra jogar futebol essa é a verdade.",
            "date": "2018-04-24T20:28:59",
            "likes": "3",
            "unlikes": "2",
            "replies": [],
            "n_replies": 0
        },
        {
            "name": "otuosBFR",
            "text": "Pimpão vestindo a 7 chega ser afronta.",
            "date": "2018-04-24T11:10:57",
            "likes": "48",
            "unlikes": "3",
            "replies": [
                {
                    "name": "Joao Branco",
                    "text": "Da mesma forma que o nanico chileno vestir a camisa 10.",
                    "date": "2018-04-24T14:26:13",
                    "likes": "22",
                    "unlikes": "2"
                },
                {
                    "name": "Smoreira",
                    "text": "Difícil escolher entre afronta ou uma comédia....",
                    "date": "2018-04-24T19:24:26",
                    "likes": "8",
                    "unlikes": "1"
                }
            ],
            "n_replies": 2
        },
        {
            "name": "Noka",
            "text": "O Brenner e o kuieza assistam bragon ball z e aprendam a fazer a técnica da fusão só assim conseguem dar um jogador",
            "date": "2018-04-24T19:21:39",
            "likes": "6",
            "unlikes": "2",
            "replies": [],
            "n_replies": 0
        },
        {
            "name": "Noka",
            "text": "O Pimpão não é o mesmo, antes ele chutava do meio do canto até do escanteio agora tá pensando muito e fazendo a escolha errada",
            "date": "2018-04-24T19:18:37",
            "likes": "5",
            "unlikes": "1",
            "replies": [],
            "n_replies": 0
        },
        {
            "name": "Ravi Giudice",
            "text": "Dois anos de contrato ! É muito castigo !",
            "date": "2018-04-24T19:02:15",
            "likes": "3",
            "unlikes": "4",
            "replies": [
                {
                    "name": "Noel",
                    "text": "O pimpao nao e ruim e atabalhoado, nao tem condições de jogar atualmente tem que se aprimorar.",
                    "date": "2018-04-24T19:16:03",
                    "likes": "6",
                    "unlikes": "1"
                }
            ],
            "n_replies": 1
        },
        {
            "name": "Arialdo Junior",
            "text": "escalou mal de mais esse pimpao e jogador muito ruim",
            "date": "2018-04-24T18:44:46",
            "likes": "3",
            "unlikes": "1",
            "replies": [],
            "n_replies": 0
        },
        {
            "name": "Arialdo Junior",
            "text": "meu deus eu nunca vi um jogador tao ruim esse pimpao caraca meu ele e ruim de mais ,botafogo nao precisa de jogador assim .ta faltando o que para valentim deixar esse cara no banco ?meu deus como esse tecnico nesse jogo do bota ele foi mal na escalacao",
            "date": "2018-04-24T18:43:50",
            "likes": "2",
            "unlikes": "2",
            "replies": [],
            "n_replies": 0
        },
        {
            "name": "Antonio Santos",
            "text": "Pimpao por favor vai embora",
            "date": "2018-04-24T18:37:12",
            "likes": "4",
            "unlikes": "3",
            "replies": [],
            "n_replies": 0
        },
        {
            "name": "Valterci Moreira",
            "text": "na boa,ele so irrita!!!!",
            "date": "2018-04-24T18:28:39",
            "likes": "3",
            "unlikes": "1",
            "replies": [],
            "n_replies": 0
        },
        {
            "name": "Nenem França",
            "text": "o gean ficou no banco , esse bochecha errou tudo ke tento , nao marcou , nao acertou um passe , time totalmente sem criatividade dai o sr valentim coloca o pachu , e nao coloca o marcus vinicius o sport E o pior time do campeonato disparado sera ke SO um vi isso pachu , bochecha e gilson com todo respeito nao tem condicoes de vestir a camisa do botafogo pessimo impate",
            "date": "2018-04-24T18:12:09",
            "likes": "10",
            "unlikes": "0",
            "replies": [],
            "n_replies": 0
        },
        {
            "name": "Cosme Silva",
            "text": "será que o nosso time assistiu o jogo de hoje ta passando pra aprender como se faz gol kkkkkkkk",
            "date": "2018-04-24T17:18:49",
            "likes": "0",
            "unlikes": "1",
            "replies": [],
            "n_replies": 0
        },
        {
            "name": "Francisco Carvalho",
            "text": "Josue Você é um \"conformado\". Nada tem a ver com educação. Ter opinião é um direito do cidadão. Se ele reclama é pq não gostou, e deseja mudança para que a coisa melhore. FORA PIMPÃO.",
            "date": "2018-04-24T16:20:52",
            "likes": "6",
            "unlikes": "1",
            "replies": [],
            "n_replies": 0
        },
        {
            "name": "Nilson Paula",
            "text": "Pensava que não existisse jogador pior do que o Pimpão e o Valença. Eis que surge uma desgraça pior: PACHU! Misericórdia.",
            "date": "2018-04-24T12:50:53",
            "likes": "45",
            "unlikes": "8",
            "replies": [
                {
                    "name": "Qi Acima",
                    "text": "Inesplicavel. Com Marcos V. Ezequiel no banco ele chama Pachu.",
                    "date": "2018-04-24T14:33:28",
                    "likes": "11",
                    "unlikes": "0"
                },
                {
                    "name": "Ribba Sousa",
                    "text": "Jogador Pachupar",
                    "date": "2018-04-24T15:02:57",
                    "likes": "4",
                    "unlikes": "0"
                },
                {
                    "name": "Philippe Leon",
                    "text": "Vcs estão de brincadeira ter que esperar 25 segundos de propaganda pra ver o vídeo.",
                    "date": "2018-04-24T15:28:28",
                    "likes": "2",
                    "unlikes": "0"
                },
                {
                    "name": "Smoreira",
                    "text": "Lindoso M.Fernandes Bochecha Pimpão Brenner Valência e ainda Marcinho Sobrinho e Gilson. Empatar já foi um milagre que se deve ao Gatito.",
                    "date": "2018-04-24T15:28:33",
                    "likes": "10",
                    "unlikes": "1"
                },
                {
                    "name": "Álvaro Rodrigues",
                    "text": "O Gatito foi quem evitou a derrota. Levamos sufoco de um time em crise e q trocou 6 jogadores para esse jogo. Francamente!!!",
                    "date": "2018-04-24T15:57:45",
                    "likes": "6",
                    "unlikes": "0"
                }
            ],
            "n_replies": 5
        },
        {
            "name": "Jorge Henrique",
            "text": "A verdade é q pru pimpão não da mais, no maximo um reserva pra entrar em último caso. Mas a culpa não é só dele, esse Buchecha tbm não tá pronto pra jogar no time principal, Ezequiel tbm não. E Valência já passou dos limites de tanto q erra. Aliás o time ontem tava igual ao time do Felipe Conceição.",
            "date": "2018-04-24T15:47:18",
            "likes": "5",
            "unlikes": "0",
            "replies": [],
            "n_replies": 0
        },
        {
            "name": "Álvaro Rodrigues",
            "text": "Q coisa grotesca e crônica essa amarelada típica do Pimpão!! Me impressiona vermos isso no profissionalismo. Na pelada isso é coisa de pipoqueiro, medroso. O cara faz isso em uma primeira-divisão??? Vergonhoso.",
            "date": "2018-04-24T15:43:28",
            "likes": "5",
            "unlikes": "1",
            "replies": [],
            "n_replies": 0
        },
        {
            "name": "Vicente Fernandes",
            "text": "Acredito que o ciclo do Pimpão chegou ao fim no Bota, resta a ele ir pra um Clube de serie B, será craque lá. Tchau valeu!",
            "date": "2018-04-24T15:34:36",
            "likes": "11",
            "unlikes": "1",
            "replies": [],
            "n_replies": 0
        },
        {
            "name": "Gilson Fonseca",
            "text": "Pimpão tem que parar de dar aqueles carrinhos malucos, vai acaber sendo expulso e prejudicando o time. Já esta na hora de Barrar o Valencia, não esta produzindo nada.",
            "date": "2018-04-24T15:24:03",
            "likes": "6",
            "unlikes": "0",
            "replies": [],
            "n_replies": 0
        },
        {
            "name": "Muda Brasil",
            "text": "Deixa o Pimpão no Botafogo, esse atleta tem credito na casa, ninguém meche nele não, deixa ele no Botafogo!",
            "date": "2018-04-24T15:19:54",
            "likes": "1",
            "unlikes": "5",
            "replies": [],
            "n_replies": 0
        },
        {
            "name": "Qi Acima",
            "text": "Pimpao jogador de segundo tempo. Para entrar de vez em quando. Tem que treinar finalizacao.",
            "date": "2018-04-24T14:31:43",
            "likes": "4",
            "unlikes": "0",
            "replies": [],
            "n_replies": 0
        },
        {
            "name": "Joenir Fonseca",
            "text": "O DURO MESMO É PAGAR OS SALÁRIOS/OUTROS/BICHOS DELE, ATÉ O FIM DO CONTRATO...!!!",
            "date": "2018-04-24T14:26:59",
            "likes": "6",
            "unlikes": "0",
            "replies": [],
            "n_replies": 0
        },
        {
            "name": "Wilber Henrique",
            "text": "Ainda bem que Valentim já percebeu que não tem condições do pimpão jogar, mas infelizmente ontem só tinha ele. O cara deu uma oportunidade, mas ele fez aquilo de novo",
            "date": "2018-04-24T14:25:54",
            "likes": "4",
            "unlikes": "0",
            "replies": [],
            "n_replies": 0
        },
        {
            "name": "Leonardo Silva",
            "text": "É que o time do botafogo é muito bom por isso pimpão faz essas graças....Não aguentamos mais léo valência no time valetin.. Jogador nulo em campo..péssimo.",
            "date": "2018-04-24T14:24:33",
            "likes": "4",
            "unlikes": "0",
            "replies": [],
            "n_replies": 0
        },
        {
            "name": "Pretoriano",
            "text": "Pimpão e Valência ninguém merece! kkk",
            "date": "2018-04-24T14:11:13",
            "likes": "5",
            "unlikes": "0",
            "replies": [],
            "n_replies": 0
        },
        {
            "name": "Jorge Lima",
            "text": "Pimpão, já esta na hora de passar no Departamento Pessoal, pega as contas e ir embora, de vez seu futebol sumiu.",
            "date": "2018-04-24T13:19:22",
            "likes": "9",
            "unlikes": "1",
            "replies": [],
            "n_replies": 0
        },
        {
            "name": "Givanildo Costa",
            "text": "Se ele chuta ia ser pra fora ou então fraquinho e o goleiro pegava, nós torcedores ia ter mais raiva, foi melhor errar o passe.",
            "date": "2018-04-24T13:10:59",
            "likes": "3",
            "unlikes": "0",
            "replies": [],
            "n_replies": 0
        },
        {
            "name": "Rogerio Dias",
            "text": "Não dá para crucificar o Pimpão, ele já nos ajudou muito. Ontem ele mandou mal, isso acontece com qualquer profissional de qualquer área.",
            "date": "2018-04-24T11:16:54",
            "likes": "9",
            "unlikes": "29",
            "replies": [
                {
                    "name": "Claudio Miranda",
                    "text": "Nós ajudou no passado. Desde o fim da libertadores do ano passado ele parece que desaprendeu a jogar futebol",
                    "date": "2018-04-24T11:42:56",
                    "likes": "7",
                    "unlikes": "1"
                },
                {
                    "name": "Ediz Andrade",
                    "text": "Rogério, me desculpe, mas futebol é momento. Pimpão desde o início do ano não vem jogando nada e ainda atrapalha. No ano passado, meteu 2 ou 3 gols importantes e já querem dizer que é craque. FORA PIMPÃO!!!",
                    "date": "2018-04-24T12:44:07",
                    "likes": "5",
                    "unlikes": "2"
                }
            ],
            "n_replies": 2
        },
        {
            "name": "Daniel Lopes",
            "text": "O problema não é chutar... pq ele já errou um assim contra o Flamengo... chutou pra fora... a questão é q é muito ruim msm!",
            "date": "2018-04-24T12:32:04",
            "likes": "8",
            "unlikes": "1",
            "replies": [],
            "n_replies": 0
        },
        {
            "name": "Breno Claudio",
            "text": "Lance de cabeça embaixo do gol, sozinho na semifinal contra o Flamengo quando ainda estava 0 a 0. Lance dentro da área na Libertadores contra o Grêmio quando ainda estava 0 a 0. Não dá mais, é jogador para Paraná, América-MG, Ceará e por aí vai. O pior é pensar que ele foi vendido e o Botafogo foi buscar de novo. Chega de Pimpão.",
            "date": "2018-04-24T11:49:34",
            "likes": "25",
            "unlikes": "1",
            "replies": [],
            "n_replies": 0
        },
        {
            "name": "Claudio Batista",
            "text": "Esse mesmo cidadao e foi fominha e nao deu o passe para o JPaulo fazer o gol quando ainda estava 0x0 no jogo de volta contra o Gremio na Liberta.... Sabe pq isso ?? Pq ele ja tinha igualado ao Jairzinho em gols na Libertadores, quis ficar na frente e deu no que deu...fomos eliminados numa competicao que fizemos uma campanha linda e que podiamos ter levado esse caneco inedito vencendo varios campeoes da libertadore, inclusive o proprio gremio....",
            "date": "2018-04-24T12:17:32",
            "likes": "15",
            "unlikes": "0",
            "replies": [],
            "n_replies": 0
        },
        {
            "name": "Zael Macedo",
            "text": "Imaginem só o Aguirre com uma bola desta roubada?? Era Barbante..",
            "date": "2018-04-24T12:09:33",
            "likes": "6",
            "unlikes": "0",
            "replies": [],
            "n_replies": 0
        },
        {
            "name": "Carlos Coelho",
            "text": "pimpão tem que vazar do botafogo isso sim",
            "date": "2018-04-24T11:48:22",
            "likes": "11",
            "unlikes": "2",
            "replies": [],
            "n_replies": 0
        },
        {
            "name": "Zaki Taam",
            "text": "É isso ai rodrigo pimpão, vc tem q aprender a chutar para o gol, vc é atacante.",
            "date": "2018-04-24T11:45:32",
            "likes": "4",
            "unlikes": "0",
            "replies": [],
            "n_replies": 0
        },
        {
            "name": "Claudio Miranda",
            "text": "Aguirre vai começar no banco contra o Grêmio ou vai começar jogando? Não sei se aguento ver Pimpão de titular de novo.",
            "date": "2018-04-24T11:43:58",
            "likes": "5",
            "unlikes": "0",
            "replies": [],
            "n_replies": 0
        },
        {
            "name": "Helio Barbosa",
            "text": "JOGO PRA JEAN",
            "date": "2018-04-24T11:42:09",
            "likes": "5",
            "unlikes": "0",
            "replies": [],
            "n_replies": 0
        },
        {
            "name": "Claudio Miranda",
            "text": "Pimpão é uma incógnita. Em jogadas que deveria tocar ele chuta, nas que deveria chutar ele toca.",
            "date": "2018-04-24T11:41:27",
            "likes": "4",
            "unlikes": "0",
            "replies": [],
            "n_replies": 0
        },
        {
            "name": "Eduardo Sales",
            "text": "cadê o Aguirre?",
            "date": "2018-04-24T10:26:55",
            "likes": "33",
            "unlikes": "0",
            "replies": [
                {
                    "name": "Pedro Henrique",
                    "text": "Deve estrear na próxima rodada.",
                    "date": "2018-04-24T10:57:46",
                    "likes": "10",
                    "unlikes": "0"
                },
                {
                    "name": "Helio Barbosa",
                    "text": "COMPRARAM O CARA BIXADO VAI DEMORAR ESTREAR",
                    "date": "2018-04-24T11:38:57",
                    "likes": "0",
                    "unlikes": "5"
                }
            ],
            "n_replies": 2
        },
        {
            "name": "Helio Barbosa",
            "text": "PIMPAO NAO É JOGADOR É PELADEIRO",
            "date": "2018-04-24T11:37:56",
            "likes": "5",
            "unlikes": "1",
            "replies": [],
            "n_replies": 0
        },
        {
            "name": "Etdofogao",
            "text": "Era só pim e depois Pam (pão), gol. Daí-me paciência...",
            "date": "2018-04-24T11:24:24",
            "likes": "0",
            "unlikes": "0",
            "replies": [],
            "n_replies": 0
        },
        {
            "name": "Patrício Rios",
            "text": "Ele teve o mérito de roubar a bola do zagueiro, criou o lance para gol. Mas, há muito tempo, ele anda sem confiança e, por isso, tem tomado decisões erradas na hora de conferir. Além disso, está muito lento para tomar decisões, o que favorece a chegada da marcação. Tem que amargar o banco por um bom tempo para recuperar a confiança perdida e a velocidade.",
            "date": "2018-04-24T10:35:55",
            "likes": "26",
            "unlikes": "1",
            "replies": [
                {
                    "name": "Alex Bawdez",
                    "text": "Ele só jogou ontem em razão da falta de opções de velocidade...",
                    "date": "2018-04-24T11:18:27",
                    "likes": "5",
                    "unlikes": "0"
                }
            ],
            "n_replies": 1
        },
        {
            "name": "Andre Lopes",
            "text": "Pimpão é muito voluntarioso, mas ele ou corre ou pensa!! Ambos não dá",
            "date": "2018-04-24T11:13:43",
            "likes": "15",
            "unlikes": "0",
            "replies": [],
            "n_replies": 0
        }
    ],
    "exception": 0,
    "url": "https://globoesporte.globo.com/futebol/times/botafogo/noticia/chuta-pimpao-atacante-do-botafogo-repete-gol-perdido-de-2017-e-irrita-torcida.ghtml",
    "team": "botafogo"
}