{
    "time": "06h48",
    "date": "01/06/2018",
    "title": "Defesa sofre três gols e vive momento de questionamento com Larghi.Sem vencer há duas partidas, Atlético-MG despenca na classificação após ocupar a liderança; treinador tem opções para mexer no sistema defensivo",
    "author": "Rafael Araújo",
    "text": [
        "O Atlético-MG levou três gols na mesma partida pela primeira vez sob o comando de Thiago Larghi. Contra o Sport, o Galo chegou a liderar o placar, mas levou dois gols em um intervalo de apenas cinco minutos, levando a virada e perdendo a segunda partida em sequência no Campeonato Brasileiro 2018.",
        "O momento do maior questionamento defensivo desde que Thiago Larghi se tornou treinador do time alvinegro, em fevereiro, acontece justamente na semana mais complicada do Galo desde o início do Brasileirão. Pela primeira vez o Atlético-MG perdeu duas partidas em sequência, deixando escapar a ponta do torneio e caindo na tabela - com a vitória do Corinthians em cima do América-MG, foi para a oitava posição.",
        "Em 14 dos 28 jogos de Thiago Larghi como treinador o time alvinegro saiu sem levar gols. Em sete partidas, levou um gol. Em seis, sofreu dois. E no 28º jogo do técnico à frente do Galo, a meta atleticana foi vazada em três oportunidades no mesmo duelo.",
        "+ Atlético-MG não segura placar e volta a perder pontos fora de casa",
        "Contra o Sport, o grande vilão para os torcedores acabou sendo o zagueiro Gabriel, que, ao lado de Bremer, não conseguiu acompanhar Rogério no lance do primeiro gol e cometeu o pênalti no lance do gol da virada.",
        "",
        "- A gente vai procurar fazer os ajustes na base do diálogo, porque não temos tempo para trabalhar, porque o jogo é no sábado. Às vezes é importante aprender com os nossos erros, ver onde estamos pecando para não perder pontos ou resultados, principalmente dentro de casa - disse o goleiro Victor após a partida no Recife.",
        "Se quiser realizar alterações no sistema defensivo, o técnico Thiago Larghi pode optar pelo retorno de Leonardo Silva ao time titular, na vaga de Gabriel ou de Bremer. Na lateral direita, Patric também está disponível. Já do lado esquerdo, Fábio Santos é o titular absoluto e, se tiver que mudar, a entrada mais provável é de Juninho."
    ],
    "comments": [
        {
            "name": "Andre Rodrigues",
            "text": "AGORA SEM ZUAÇÃO, POR NO GOOGLE,TIME MAIOR CHACOTA DO BRASIL,KKK,CONFERE LA",
            "date": "2018-06-01T15:29:57",
            "likes": "6",
            "unlikes": "2",
            "replies": [
                {
                    "name": "Ronaldo Porto",
                    "text": "Cara fui conferir e, aí apareceu vários vídeos e reportagens indicando o galão da Marcia como o time mais zoado do mundo kkkkkkkkkkkkkkkkkkkkkkkkkkkkkkkkkkkkkkkkkkkkk",
                    "date": "2018-06-01T18:37:22",
                    "likes": "4",
                    "unlikes": "2"
                },
                {
                    "name": "Andre Rodrigues",
                    "text": "E SÓ CHACOTA PRA CIMA DESSAS FRANGAS KKKKKKKKKKK",
                    "date": "2018-06-02T09:56:58",
                    "likes": "0",
                    "unlikes": "0"
                }
            ],
            "n_replies": 2
        },
        {
            "name": "Bruno Cesar",
            "text": "essas frangas são comédia demais.. kkk",
            "date": "2018-06-01T11:21:37",
            "likes": "5",
            "unlikes": "3",
            "replies": [
                {
                    "name": "Oltamir Bertolino",
                    "text": "CAM= Cansado de Apanhar do Mengo. kkkkkkkkkkkkkkkk",
                    "date": "2018-06-01T21:29:47",
                    "likes": "4",
                    "unlikes": "1"
                }
            ],
            "n_replies": 1
        },
        {
            "name": "Marcio Oliveira",
            "text": "Duvida cruel - ir ao Indepa amanhã ou passear com meu cachorro. ? Acho que vou optar é pelo passeio pois o meu cachorro não me faz raiva e nem me envergonha. Ele jamais dará motivos para no dia seguinte aguentar zoeira e humilhação de colegas que torcem para times rivais.",
            "date": "2018-06-01T08:58:47",
            "likes": "1",
            "unlikes": "3",
            "replies": [
                {
                    "name": "Leonardo",
                    "text": "Só trouxa perde tempo indo do Independência.",
                    "date": "2018-06-01T11:50:59",
                    "likes": "0",
                    "unlikes": "2"
                },
                {
                    "name": "Oltamir Bertolino",
                    "text": "Independência também com condinome de Horto é aquele estadio que apagam os reflectores?",
                    "date": "2018-06-01T21:28:17",
                    "likes": "1",
                    "unlikes": "0"
                }
            ],
            "n_replies": 2
        },
        {
            "name": "Alex Pereira",
            "text": "Gabriel não é zagueiro para ser titular do Galo, apenas um bom reserva. A diretoria deve estar achando que ele é o novo Jemerson, tá na hora do Maidana assumir a titularidade.",
            "date": "2018-06-01T09:41:06",
            "likes": "21",
            "unlikes": "6",
            "replies": [
                {
                    "name": "Leonardo",
                    "text": "Jemerson também foi uma enganação inventada pela galopress. A galopress vive ludibriando os próprios torcedores do Atlético-MG, que acham que tem um time nível A, mas o que vemos é que a realidade não aceita desaforo.",
                    "date": "2018-06-01T11:49:18",
                    "likes": "3",
                    "unlikes": "12"
                },
                {
                    "name": "Oltamir Bertolino",
                    "text": "O melhor zagueiro do Brasil chama DEDÉ",
                    "date": "2018-06-01T21:23:10",
                    "likes": "2",
                    "unlikes": "1"
                }
            ],
            "n_replies": 2
        },
        {
            "name": "Andre Rodrigues",
            "text": "AQUI QUE E A PAGINA DO BOTAFOGO MG ? KKKKKKKK",
            "date": "2018-06-01T12:10:05",
            "likes": "8",
            "unlikes": "3",
            "replies": [
                {
                    "name": "Cesari",
                    "text": "Não ! Mas BOTA-OVO-MG...sim !",
                    "date": "2018-06-01T14:11:21",
                    "likes": "4",
                    "unlikes": "2"
                },
                {
                    "name": "Jose Pereira",
                    "text": "Aqui não tem espaço para as simpatizantes do SÃO CAETANO de MINAS.",
                    "date": "2018-06-01T17:39:39",
                    "likes": "2",
                    "unlikes": "2"
                },
                {
                    "name": "Oltamir Bertolino",
                    "text": "É do Botafogo de Minas, por isso perde do Mengão, siga o líder.",
                    "date": "2018-06-01T21:14:45",
                    "likes": "0",
                    "unlikes": "0"
                }
            ],
            "n_replies": 3
        },
        {
            "name": "Luis Modesto",
            "text": "Freguês se esqueceu do resultado do último clássico.kkkkk",
            "date": "2018-06-01T15:10:31",
            "likes": "2",
            "unlikes": "3",
            "replies": [
                {
                    "name": "Andre Rodrigues",
                    "text": "essa e a diferença de quem comemora jogo ,pra quem comemora titulo",
                    "date": "2018-06-01T15:43:37",
                    "likes": "6",
                    "unlikes": "1"
                },
                {
                    "name": "Jose Pereira",
                    "text": "Qual título que vc comemorou esse ano? fala Maria!",
                    "date": "2018-06-01T17:34:52",
                    "likes": "2",
                    "unlikes": "0"
                }
            ],
            "n_replies": 2
        },
        {
            "name": "Sergio Vidal",
            "text": "time pra chape victor, emerson , brenner , maidana , juninho , elias blanco , cazares , luan , ricardo oliveira e roger guedes",
            "date": "2018-06-01T13:59:36",
            "likes": "4",
            "unlikes": "3",
            "replies": [
                {
                    "name": "Levi Tancredo",
                    "text": "Gabriél não pode sair do time não foi penalti,",
                    "date": "2018-06-01T17:07:46",
                    "likes": "1",
                    "unlikes": "2"
                }
            ],
            "n_replies": 1
        },
        {
            "name": "Jose Faustino",
            "text": "Depois q colocaram este Emerson na lateral, o time ficou vulnerável na marcação. E ele também não é tão bom no ataque. Resumindo : Melhor jogar com Patrick. Time mais consistente na defesa.",
            "date": "2018-06-01T17:05:33",
            "likes": "0",
            "unlikes": "0",
            "replies": [],
            "n_replies": 0
        },
        {
            "name": "Jorge Magalhães",
            "text": "Copiei o comentário abaixo, só o treinador não vê. Desde o ano passado venho falando que é o pior jogador do galo, em todos os jogos aconteciam(e acontecem) gols por falha dele. Notem que só o nosso treinador não enxerga isso, todos os bons treinadores ganham os jogos do galo por aquele lado. \"Se o ataque adversário explora a lateral esquerda do galo, Fábio Santos corre de um lado para outro fingindo buscar marcação. Não marca e nem combate, foge do adversário. O técnico não consegue, ou não quer ver essa omissão do jogador.\"",
            "date": "2018-06-01T16:29:52",
            "likes": "6",
            "unlikes": "0",
            "replies": [],
            "n_replies": 0
        },
        {
            "name": "Andre Rodrigues",
            "text": "SAÍRAM DA SULAMERICANA E COPA DO BRASIL,PRA PASSAR VERGONHA SÓ NO BRASILEIRO KKK",
            "date": "2018-06-01T15:22:15",
            "likes": "15",
            "unlikes": "0",
            "replies": [
                {
                    "name": "Dionisio Santos",
                    "text": "Cuida das Marias deixa o maior de Minas em paz.",
                    "date": "2018-06-01T15:52:17",
                    "likes": "4",
                    "unlikes": "4"
                }
            ],
            "n_replies": 1
        },
        {
            "name": "Sergio Vidal",
            "text": "tenho pavor desse lateral não marca e quando apoia erra todos os cruzamentos",
            "date": "2018-06-01T13:58:32",
            "likes": "10",
            "unlikes": "3",
            "replies": [
                {
                    "name": "Andre Rodrigues",
                    "text": "HUMMMM A MENINA TEM PAVOR KKKKK",
                    "date": "2018-06-01T14:31:20",
                    "likes": "6",
                    "unlikes": "1"
                },
                {
                    "name": "Moacir Belo",
                    "text": "Em time que está ganhando não se mexe,falem o que quiserem ,mais com Patrick em campo , o time estava indo aos trancos e barrancos mais não perdia, e porque sempre substituir o Blanco, e quando ele sai os erros acontecem e a derrota é certa.",
                    "date": "2018-06-01T15:29:27",
                    "likes": "5",
                    "unlikes": "2"
                }
            ],
            "n_replies": 2
        },
        {
            "name": "Anaemuriel Costa",
            "text": "KK na minha opinião n deve mudar nada as frangas tão num caminho certo hehehe",
            "date": "2018-06-01T13:38:08",
            "likes": "6",
            "unlikes": "4",
            "replies": [
                {
                    "name": "Phelipe Csatro",
                    "text": "hahahahhahahahhaha verdade",
                    "date": "2018-06-01T14:21:35",
                    "likes": "1",
                    "unlikes": "1"
                }
            ],
            "n_replies": 1
        },
        {
            "name": "Andre Rodrigues",
            "text": "O MEDICO DISSE QUE EU PRECISAVA RIR UM POUCO,PERGUNTEI ONDE ? E ELE ME DISSE NA PÁGINA DO ATLETICO MG KKKK",
            "date": "2018-06-01T11:37:59",
            "likes": "7",
            "unlikes": "7",
            "replies": [
                {
                    "name": "Carlos Oliveira",
                    "text": "E eu vou rir com sua mãe.",
                    "date": "2018-06-01T12:52:38",
                    "likes": "4",
                    "unlikes": "2"
                },
                {
                    "name": "Antonio Fonseca",
                    "text": "ANDRE RODRIGUES..PERGUNTA PRO SE MEDICO SE VOCÊ TEM QUE SENTAR NUMA NABA GRANDE...AI VOCÊ VEM AQUI TAMBÉM, PODE TRAZER SUA MÃE QUE TEM PRA ELA TAMBÉM.",
                    "date": "2018-06-01T13:42:55",
                    "likes": "1",
                    "unlikes": "2"
                },
                {
                    "name": "Cesari",
                    "text": "Quiéisso?!!! O médico do cara falô e o cara é que tem culpa?",
                    "date": "2018-06-01T14:07:24",
                    "likes": "2",
                    "unlikes": "1"
                },
                {
                    "name": "Phelipe Csatro",
                    "text": "Frangas depenadas e desesperadas!!!!",
                    "date": "2018-06-01T14:21:17",
                    "likes": "2",
                    "unlikes": "1"
                }
            ],
            "n_replies": 4
        },
        {
            "name": "Peter Spencer",
            "text": "Por que os torcedores do atlético-MG chamam o atlético-MG pelo nome de UMA AVE GALINÁCEA que DEFECA, que URINA e que TRANSA pela CLOACA?!",
            "date": "2018-06-01T09:24:53",
            "likes": "15",
            "unlikes": "13",
            "replies": [
                {
                    "name": "Jarbas Fernandes",
                    "text": "e porque vc tem inveja do simbolo do Atletico-MG ? claro porque Galo e um nome forte e mete medo nas marias ne ?",
                    "date": "2018-06-01T09:27:57",
                    "likes": "3",
                    "unlikes": "3"
                },
                {
                    "name": "Marcio Oliveira",
                    "text": "É o mesmo querer saber como você veio ao mundo visto que foste c a g a d o e não p a r i d o .",
                    "date": "2018-06-01T09:39:11",
                    "likes": "3",
                    "unlikes": "1"
                },
                {
                    "name": "Peter Spencer",
                    "text": "O atlético-MG causou muito medo no Cruzeiro nos SEIS a UM de 2011?!",
                    "date": "2018-06-01T09:44:09",
                    "likes": "4",
                    "unlikes": "3"
                },
                {
                    "name": "Celso Rossy",
                    "text": "MARIA POR AQUI???",
                    "date": "2018-06-01T09:44:52",
                    "likes": "2",
                    "unlikes": "4"
                },
                {
                    "name": "Peter Spencer",
                    "text": "galo QUEER.",
                    "date": "2018-06-01T09:53:30",
                    "likes": "3",
                    "unlikes": "1"
                },
                {
                    "name": "Peter Spencer",
                    "text": "frangas ROSAS.",
                    "date": "2018-06-01T09:57:30",
                    "likes": "4",
                    "unlikes": "2"
                },
                {
                    "name": "Marcelo Gomes",
                    "text": "Kkkkkkkkkkkkkkk 6a1o rosa da massa fresca kkkkkkkkkkkkkkkkkkkkk.",
                    "date": "2018-06-01T10:01:10",
                    "likes": "3",
                    "unlikes": "2"
                },
                {
                    "name": "Ranieri Armondes",
                    "text": "E o 9 x2? Se tiver esquecido consulte o almanaque do seu tímido povo!!",
                    "date": "2018-06-01T10:12:47",
                    "likes": "4",
                    "unlikes": "2"
                },
                {
                    "name": "Peter Spencer",
                    "text": "É verdade que os 09 a 02 de 1927 foram VÁLIDOS por uma competição AMADORA e MUNICIPAL?! E os SEIS a UM de 2011?!",
                    "date": "2018-06-01T10:25:16",
                    "likes": "3",
                    "unlikes": "2"
                },
                {
                    "name": "Gilberto",
                    "text": "Agora sim, até que em fim a Maria aceitou, como as pessoas dizem: Aceita que dói menos.",
                    "date": "2018-06-01T10:39:58",
                    "likes": "2",
                    "unlikes": "2"
                },
                {
                    "name": "Peter Spencer",
                    "text": "Então, as FRANGAS rosas ADMITEM de FORMA PÚBLICA que os 09 a 02 de 1927 foram VÁLIDOS por campeonato AMADOR e MUNICIPAL?! E os SEIS a UM de 2011?!",
                    "date": "2018-06-01T10:43:51",
                    "likes": "3",
                    "unlikes": "4"
                },
                {
                    "name": "Leonardo",
                    "text": "Cara, se eu tivesse que resgatar uma goleada da década de 20 (quando a bola era de bexiga de boi), para fazer frente há uma goleada recente e humilhante que meu time tenha tomado, eu mudava de time. É muito vergonhoso.",
                    "date": "2018-06-01T11:46:06",
                    "likes": "0",
                    "unlikes": "3"
                },
                {
                    "name": "Peter Spencer",
                    "text": "Afinal de contas, o NOME do clube é atlético-MG ou AVE GALINÁCEA?!",
                    "date": "2018-06-01T12:47:38",
                    "likes": "0",
                    "unlikes": "4"
                }
            ],
            "n_replies": 13
        },
        {
            "name": "Edson Valadares",
            "text": "FORA ALEXANDRE GALLO !!! E LEVE COM VC ESSAS BOMBAS QUE CONTRATOU; MATEUS GALDEZANI, TOMAS ANDRADE, E CIA.",
            "date": "2018-06-01T14:08:51",
            "likes": "7",
            "unlikes": "0",
            "replies": [],
            "n_replies": 0
        },
        {
            "name": "Seisaum Nelas",
            "text": "Já levou de Seis antes. Muito pior",
            "date": "2018-06-01T13:59:22",
            "likes": "0",
            "unlikes": "0",
            "replies": [],
            "n_replies": 0
        },
        {
            "name": "Sergio Vidal",
            "text": "fabio santos ja era essa diretoria competente ainda não viu isso jogador superestimado as vezes ate o torcedor e enganado elele simplismente horriveel em 4 anos de galo so deu uma ou duas assistencia se não me engano",
            "date": "2018-06-01T13:57:52",
            "likes": "8",
            "unlikes": "0",
            "replies": [],
            "n_replies": 0
        },
        {
            "name": "Sergio Vidal",
            "text": "tira esse fabio santos fica emerson brenner gabriel e junin ho",
            "date": "2018-06-01T13:56:02",
            "likes": "7",
            "unlikes": "1",
            "replies": [],
            "n_replies": 0
        },
        {
            "name": "Guilherme Marques",
            "text": "Vai cair com certeza",
            "date": "2018-06-01T10:10:32",
            "likes": "7",
            "unlikes": "3",
            "replies": [],
            "n_replies": 0
        },
        {
            "name": "Jose Fonseca",
            "text": "Não muda a defesa não pelo amor de Deus!,deixa essa dupla que tá aí,se for pra tirar que tire o Gabriel,o Galo tem que dar ritimo a uma defesa jovem pra pegar experiência por que voltar com o Léo Silva não dá,tem que ser banco.Dos três gols sofridos só o primeiro que pode culpar os zagueiros porque os outros dois não.Lances atípicos: bola desviada e bola na mão.",
            "date": "2018-06-01T11:53:59",
            "likes": "7",
            "unlikes": "6",
            "replies": [
                {
                    "name": "Antonio Deus",
                    "text": "Zagueiros e laterais deixam muito a desejar.",
                    "date": "2018-06-01T13:26:22",
                    "likes": "5",
                    "unlikes": "2"
                }
            ],
            "n_replies": 1
        },
        {
            "name": "Cleber",
            "text": "MAS ISSO E um RESULTADO DO NOSSO \"NEPOBURROCENO\", que recebeu um time vencedor... consegiu com seu sonho IMAGINARIO, MONTAR UM TIME DE VELHOS E ULTRAPASSADOS JOGADORES, que nao deu certo... o mesmo e mediocre sonho da selegalo - lembra.. cabe a o novo PRESIDA fazer um trabalho de base. consiciente finaceiramente e nao se preocupar tanto.... ACHO O LARGUI INESPERIENTE, mas ta fazendo o time jogar... e o galo nao e melhor elenco.... VAO GALOOOOOOOOOOOOOOOOO....",
            "date": "2018-06-01T13:24:11",
            "likes": "1",
            "unlikes": "2",
            "replies": [],
            "n_replies": 0
        },
        {
            "name": "Julio Souza",
            "text": "O problema está nas laterais, nas duas. E esse fabio santos é ruim demais.",
            "date": "2018-06-01T12:45:32",
            "likes": "7",
            "unlikes": "4",
            "replies": [
                {
                    "name": "Antonio Deus",
                    "text": "Se o ataque adversário explora a lateral esquerda do galo, Fábio Santos corre de um lado para outro fingindo buscar marcação. Não marca e nem combate, foge do adversário. O técnico não consegue, ou não quer ver essa omissão do jogador.",
                    "date": "2018-06-01T13:20:10",
                    "likes": "7",
                    "unlikes": "1"
                }
            ],
            "n_replies": 1
        },
        {
            "name": "Marcos Lucena",
            "text": "Vamos golear a Chape! Montei o meu time no Cartola TODO GALO. Acho que nessa rodada o Galo será soberano. Até tu Larghi !",
            "date": "2018-06-01T10:02:31",
            "likes": "14",
            "unlikes": "8",
            "replies": [
                {
                    "name": "Leonardo",
                    "text": "KKKKKKKKKKKKKKKKKK",
                    "date": "2018-06-01T11:47:46",
                    "likes": "1",
                    "unlikes": "1"
                },
                {
                    "name": "Roberto Lacerda",
                    "text": "Tmj nessa... Vamos Galooooo",
                    "date": "2018-06-01T12:11:38",
                    "likes": "3",
                    "unlikes": "0"
                },
                {
                    "name": "Orlando Martins",
                    "text": "Esta esperança é o que nos acalenta, mas não esqueçamos, ano passado perdemos por vacilos semelhantes, e nos dois últimos jogos se quer marcamos 1 gol.",
                    "date": "2018-06-01T12:44:23",
                    "likes": "3",
                    "unlikes": "1"
                },
                {
                    "name": "Arthur Antonio",
                    "text": "Temos que pontuar o máximo possível em casa, a copa é semana que vem já!!! AVANTE MEU GALO!!!",
                    "date": "2018-06-01T13:05:58",
                    "likes": "1",
                    "unlikes": "0"
                }
            ],
            "n_replies": 4
        },
        {
            "name": "José Maria",
            "text": "Tem LURDINHA que detesta o apelido de LURDINHA. Mas é um apelido legal, e a maioria gosta muito. Outro dia uma LURDINHA me falou que adooora o apelido dela.",
            "date": "2018-06-01T12:00:19",
            "likes": "2",
            "unlikes": "1",
            "replies": [
                {
                    "name": "Wagner Couto",
                    "text": "e mesmo maria que coisa",
                    "date": "2018-06-01T12:43:09",
                    "likes": "0",
                    "unlikes": "0"
                }
            ],
            "n_replies": 1
        },
        {
            "name": "Andre Rodrigues",
            "text": "DIGITEI NO GOOGLE, LIDER NA 5 RODADA,PAREI AQUI, KKKKKKKKKKKKK",
            "date": "2018-06-01T10:07:37",
            "likes": "7",
            "unlikes": "0",
            "replies": [
                {
                    "name": "Leonardo",
                    "text": "Depois da Copa você digita \"zona de rebaixamento\". Você vai parar na mesma página.",
                    "date": "2018-06-01T11:47:19",
                    "likes": "3",
                    "unlikes": "1"
                },
                {
                    "name": "Andre Rodrigues",
                    "text": "KKKKKKKKKKKKKKK SO CHACOTAS DESSAS FRANGAS",
                    "date": "2018-06-01T12:23:10",
                    "likes": "1",
                    "unlikes": "0"
                },
                {
                    "name": "Celso Morais",
                    "text": "Digitei página cheia de Marias fofoqueiras e caí na página do cruzeiro e logo me indicou que elas vivem preocupadas na página do Galo",
                    "date": "2018-06-01T12:31:10",
                    "likes": "2",
                    "unlikes": "0"
                }
            ],
            "n_replies": 3
        },
        {
            "name": "Celso Morais",
            "text": "O mais difícil aqui nos noticiários do Galo é ler os comentários sem encontrar 80% de cruzeirenses, agora por favor, verifiquem nos noticiários do time deles e vejam se tem algum atleticanos por lá.... Não entendo esta necessidade de auto afirmação deles",
            "date": "2018-06-01T12:21:08",
            "likes": "9",
            "unlikes": "0",
            "replies": [],
            "n_replies": 0
        },
        {
            "name": "Orlando Martins",
            "text": "Boa tarde, alguns membros da diretoria e da comissão técnica deveriam fazer como Pedro Parente EX Presidente da Petrobras , entregar carta de demissão. Vale também pra alguns Pseudos jogadores.",
            "date": "2018-06-01T12:15:14",
            "likes": "2",
            "unlikes": "0",
            "replies": [],
            "n_replies": 0
        },
        {
            "name": "Thiago Santos",
            "text": "Hora de trazer tardelli e bernard!!! vamos diretoria nosso time estava entre os grandes, desse jeito vamos voltar a ser medianos. Como Fluminense, Atletico Paranaense, Vasco, Botafogo, etc.",
            "date": "2018-06-01T12:08:27",
            "likes": "2",
            "unlikes": "1",
            "replies": [],
            "n_replies": 0
        },
        {
            "name": "Andre Rodrigues",
            "text": "PRECISA RIR UM POUCO? VENHA PRA PAGINA DO ATLETICO MG ,RINDO ATE 2050 KKKK",
            "date": "2018-06-01T12:04:59",
            "likes": "2",
            "unlikes": "1",
            "replies": [],
            "n_replies": 0
        },
        {
            "name": "Andre Rodrigues",
            "text": "PRIMEIRA VEZ QUE EU VEJO UMA CALOPICITA (GUEDES)JOGAR NO GALINHO KKK",
            "date": "2018-06-01T12:04:12",
            "likes": "1",
            "unlikes": "0",
            "replies": [],
            "n_replies": 0
        },
        {
            "name": "Cesari",
            "text": "Nem com 8 partidas em casa nas 12 primeiras rodadas.....nem assim...o INSETO ENGRENA ???",
            "date": "2018-06-01T08:13:05",
            "likes": "5",
            "unlikes": "9",
            "replies": [
                {
                    "name": "Sergio Oliveira",
                    "text": "Vai dar bom dia lá na página das marias o mané!!!",
                    "date": "2018-06-01T08:59:12",
                    "likes": "1",
                    "unlikes": "0"
                },
                {
                    "name": "Leonardo",
                    "text": "O inseto só vai engrenar na série B no ano que vem.",
                    "date": "2018-06-01T11:50:10",
                    "likes": "0",
                    "unlikes": "1"
                }
            ],
            "n_replies": 4
        },
        {
            "name": "Gauss Oliveira",
            "text": "O que deixa o torcedor irado é a melhor insistência ou falta de transparência da diretoria...Prlo demonstrado até agora o Bremer tem mais de amadurecer profissionalmente que o Gabriel. Todos jogadores falham. Mas o Gabriel falha muito. E por displicência. Aí ele vai lá na área numa cobrança de escanteio faz um gol e tá tudo certo....brincadeira né. Se tivesse atuado bem, não terIa acontecido a bandeira do Patric, o gol do Flamengo e agora o pênalti do Sport...O Gabriel está em todas...",
            "date": "2018-06-01T08:22:36",
            "likes": "10",
            "unlikes": "5",
            "replies": [
                {
                    "name": "flavio informatica",
                    "text": "e o Adilson que fez uma falta ridícula no ataque invalidando um gol por pura infantilidade? e o cazares que anda em campo? falta é garra para essa turma além de um pouco de futebol... concordo com você o Gabriel não está a altura do Bremer.",
                    "date": "2018-06-01T09:57:45",
                    "likes": "6",
                    "unlikes": "0"
                },
                {
                    "name": "Eugenio Paiva",
                    "text": "CONCORDO COM VC OS CARAS ESTAO ANDANDO NO CAMPO LUAN E ADILSON E BLANCO SE MATA PARA CAZARES E GUEDES OS CARAS NAO MARCA",
                    "date": "2018-06-01T11:41:05",
                    "likes": "3",
                    "unlikes": "1"
                }
            ],
            "n_replies": 2
        },
        {
            "name": "Thiago Santos",
            "text": "Comece procurando um bom zagueiro, vende Gabriel e busca um de qualidade fora do pais. Vende o Cazares ainda que tem mercado e invista ou Hernanes ou em Ricardo Goulart. Tem que reforçar para motivar o time, do jeito não vamos classificar para libertadores. Campeão tem que ser muito iludido, vamos diretoria antes que a torcida comece a agir!",
            "date": "2018-06-01T08:21:06",
            "likes": "16",
            "unlikes": "12",
            "replies": [
                {
                    "name": "Antonio Deus",
                    "text": "No jogo contra o sport Fábio Santos não marcou ninguém, não fez um único combate, corria de um lado para outro fingindo que marcava,comprometia o setor defensivo e deixava a \"bomba\" estourar em cima do Gabriel.",
                    "date": "2018-06-01T10:42:56",
                    "likes": "5",
                    "unlikes": "1"
                },
                {
                    "name": "Eugenio Paiva",
                    "text": "NAO E SO FABIO SANTOS CAZRES TAMBEM NAO MARCA",
                    "date": "2018-06-01T11:37:01",
                    "likes": "5",
                    "unlikes": "1"
                }
            ],
            "n_replies": 8
        },
        {
            "name": "Fwfred",
            "text": "Kkkkkkkkkk será que alguém mesmo acreditava que esse nanico iria liderar por muito tempo??",
            "date": "2018-06-01T11:28:25",
            "likes": "0",
            "unlikes": "0",
            "replies": [],
            "n_replies": 0
        },
        {
            "name": "Bruno Cesar",
            "text": "essas frangas são comédias demais ... kkkk",
            "date": "2018-06-01T11:22:06",
            "likes": "3",
            "unlikes": "5",
            "replies": [],
            "n_replies": 0
        },
        {
            "name": "Bruno Cesar",
            "text": "essas frangas são comédia demais.. kkkk",
            "date": "2018-06-01T11:15:24",
            "likes": "3",
            "unlikes": "3",
            "replies": [],
            "n_replies": 0
        },
        {
            "name": "Jonas Coimbra",
            "text": "patrick ajuda muito a marcação",
            "date": "2018-06-01T07:58:51",
            "likes": "8",
            "unlikes": "10",
            "replies": [
                {
                    "name": "Luiz Silva",
                    "text": "grande problema e que o trinador acha que esta bem mas sempre disse futebol bonito e aquele de tres pontos não interessa toque e posse de bola é resultado como faz o time do mano so atleticano mas tenho que adimitir que treinador igual o das maria e dificil",
                    "date": "2018-06-01T10:38:23",
                    "likes": "1",
                    "unlikes": "0"
                },
                {
                    "name": "Pierre Souza",
                    "text": "Torcedores Atleticanos, está defesa é horrível o lateral fraquíssimo só atrapalha, o tal do Adilson pense num jogador ruim e sem falar neste treinado de vocês não sabe mexer e como deixar Elias, Patrick no banco para esses jogadores ruins no segundo tempo tirou o Luan se estivesse cansado mesmo assim é um dos melhores e pegou o atacante mais perigoso Roger Guedes colocou no meio e sim continuar assim vão dá graças a Deus de pegar sul americana.",
                    "date": "2018-06-01T11:01:38",
                    "likes": "0",
                    "unlikes": "0"
                }
            ],
            "n_replies": 2
        },
        {
            "name": "Marcelo Gomes",
            "text": "Melhor 3 do que 6, 5 ou 14 né frangas ??? KKKKKK.",
            "date": "2018-06-01T10:03:50",
            "likes": "2",
            "unlikes": "1",
            "replies": [],
            "n_replies": 0
        },
        {
            "name": "Luiz Bento",
            "text": "Mudanças são sempre bem vindas. Principalmente quando o time é limitado.",
            "date": "2018-06-01T09:57:24",
            "likes": "0",
            "unlikes": "0",
            "replies": [],
            "n_replies": 0
        },
        {
            "name": "Marcio Oliveira",
            "text": "BOMMMMM DIAAAAAAA, FRANGASSSSSSSS!!!!",
            "date": "2018-06-01T08:52:08",
            "likes": "1",
            "unlikes": "3",
            "replies": [
                {
                    "name": "Geovanny Costa",
                    "text": "Falar em frangas....a mamae vai bem neh!",
                    "date": "2018-06-01T09:27:36",
                    "likes": "0",
                    "unlikes": "0"
                },
                {
                    "name": "Vinicius Berdnaski",
                    "text": "Bom dia raposinha vaidosa.!!!",
                    "date": "2018-06-01T09:31:21",
                    "likes": "1",
                    "unlikes": "0"
                }
            ],
            "n_replies": 2
        },
        {
            "name": "Fabiano Oliveira",
            "text": "sem jogador não vai.",
            "date": "2018-06-01T08:02:14",
            "likes": "9",
            "unlikes": "1",
            "replies": [
                {
                    "name": "Sergio Oliveira",
                    "text": "O Jonas me ajuda ai . Patrick? Vc torce pra quem meu chapa?",
                    "date": "2018-06-01T08:59:53",
                    "likes": "2",
                    "unlikes": "1"
                }
            ],
            "n_replies": 1
        }
    ],
    "exception": 0,
    "url": "https://globoesporte.globo.com/futebol/times/atletico-mg/noticia/defesa-sofre-tres-gols-pela-1-vez-e-vive-momento-de-questionamento-com-larghi.ghtml",
    "team": "atlético-mg"
}