{
    "time": "20h27",
    "date": "15/11/2018",
    "title": "Michel explica gol contra em empate do Grêmio com São Paulo: \"Falta de sorte\".Volante desvia bola para o próprio gol gremista e decreta o 1 a 1 no Morumbi",
    "author": "GloboEsporte.com",
    "text": [
        "Uma infelicidade impediu que o Grêmio vencesse o São Paulo na noite desta quinta-feira, no Morumbi, pela 34ª rodada do Brasileirão. Foi assim que o volante Michel caracterizou o lance em que marcou gol contra no empate em 1 a 1, uma falta de sorte. Mas o ponto somado saiu de bom tamanho, já que a equipe mantém a quarta colocação pelo número de vitórias.",
        "O Grêmio saiu na frente com Everton, após completar de cabeça cruzamento de Madson. E o triunfo até se mantinha tranquilo, sem que o adversário apresentasse chances de empatar. Porém, em uma bola que parecia cair nas mãos do goleiro Paulo Victor, Michel cabeceou para a própria meta.",
        "– Foi uma falta de sorte, eu estava na jogada. Paulo Victor saiu junto, acabamos trombando. Falta de costume, não. Se fosse um zagueiro, poderia ter acontecido a mesma coisa. Subi junto com o Paulo Victor, não deu tempo de nos comunicar. Infelicidade – explicou o meio-campista.",
        "Devido à lesão muscular de Paulo Miranda ainda no primeiro tempo, Michel acabou deslocado para a zaga – o time não tinha jogadores da posição no banco de reservas. Na próxima partida, no domingo, contra a Chapecoense, a tendência é que o volante seja novamente utilizado ao lado de Geromel, caso Miranda não tenha condições. Bressan não deve ser aproveitado, já que está afastado após a eliminação da Libertadores e não tem clima com a torcida.",
        "- A gente sabia da dificuldade. Numa infelicidade eles empataram, mas o pontinho fora foi muito importante - completou Michel.",
        "O Grêmio retorna nesta sexta-feira de São Paulo, próximo do meio-dia. Um treinamento está marcado para 15h30 no CT Luiz Carvalho. Com o empate, segue no G-4, à frente justamente do São Paulo, que tem os mesmos 59 pontos."
    ],
    "comments": [
        {
            "name": "Alexandre Carvalho",
            "text": "Estava sozinho na jogada. Foi pra bola de frente pro gol. Errou. Bola pra frente. Quanto a Renato, acho que deve ficar, mas se não der, vida que segue. Abraço.",
            "date": "2018-11-16T23:14:43",
            "likes": "0",
            "unlikes": "0",
            "replies": [],
            "n_replies": 0
        },
        {
            "name": "Eliane Silva",
            "text": "Bressan tbm foi falta de sorte e a torcida crucificou o cara.",
            "date": "2018-11-16T19:27:32",
            "likes": "0",
            "unlikes": "0",
            "replies": [],
            "n_replies": 0
        },
        {
            "name": "Marcos",
            "text": "Sem dúvida faltou comunicação, falha.",
            "date": "2018-11-16T11:32:21",
            "likes": "0",
            "unlikes": "0",
            "replies": [],
            "n_replies": 0
        },
        {
            "name": "João Hornes",
            "text": "Esse Michel não é de hoje que não assume responsabilidade, o elenco sempre blinda um ao outro, assumem culpas que nem são deles, apoiam até o Bressan, já este Michel sempre joga nas costas dos outros, na primeira oportunidade financeira ele deixa o Gremio, cara sem nenhum comprometimento com o clube.",
            "date": "2018-11-16T11:06:27",
            "likes": "0",
            "unlikes": "0",
            "replies": [],
            "n_replies": 0
        },
        {
            "name": "Lauro Marinoso",
            "text": "Falta de sorte uma ova, foi é muito mal mesmo. Como pode cabecear pra frente dentro da pequena área? Idiota.",
            "date": "2018-11-15T21:37:59",
            "likes": "0",
            "unlikes": "0",
            "replies": [
                {
                    "name": "Roger Ramalho",
                    "text": "Acontece. Bola pra frente e trabalhem pra que não se repita! Vamos tricolor.",
                    "date": "2018-11-16T11:01:26",
                    "likes": "0",
                    "unlikes": "0"
                }
            ],
            "n_replies": 1
        },
        {
            "name": "Jucemar Rampinelli",
            "text": "Falta de sorte? Trombou com o goleiro? Ele acha que todo mundo soube do gol ouvindo transmissão de rádio? Diz pra ele que existe TV. Cabeceou consciente...sem pressão...sozinho...ruindade mesmo! Paulo Vitor foi fazer o que ali? Outra naba esse goleiro...dois patetas se chocando...artistas de circo.",
            "date": "2018-11-16T10:57:28",
            "likes": "0",
            "unlikes": "0",
            "replies": [],
            "n_replies": 0
        },
        {
            "name": "Jose Pessano",
            "text": "O MEU TIME TOMA UNS GOLS BOBOS A PARTIR DOS 35 + OU - SEGUNDO TEMPO, FALTAM 10 E FALTA MUITO FOCO, OS CARAS NÃO TÃO NEM AÍ, NO PRÓXIMO JOGO JÁ VÃO ESTAR NOVAMENTE FAZENDO CAGAD.. HOMÉRICAS. \"\"NO PRÓXIMO VAMOS ESTAR MAIS FOCADOS, ETC, BLA, BLA, BLA\".",
            "date": "2018-11-16T10:51:34",
            "likes": "0",
            "unlikes": "0",
            "replies": [],
            "n_replies": 0
        },
        {
            "name": "Marcelo Gomes",
            "text": "O PIOR QUE ELE QUIS DIVIDIR A SUA FALHA COM O PAULO VITOR DIZENDO QUE O GOLEIRO TROMBOU COM ELE!!",
            "date": "2018-11-16T10:44:00",
            "likes": "0",
            "unlikes": "0",
            "replies": [],
            "n_replies": 0
        },
        {
            "name": "Marcelo Gomes",
            "text": "ONTEM NOVAMENTE TEVE A MÃO DE RENATO NAQUELE JOGO RUIM DO GREMIO POIS SE FOSSE QUALQUER OUTRO TREINADOR CHAMARIA UM ZAGUEIRO DA BASE PARA COMPOR O GRUPO!!MAS COMO RENATO SE ACHA A ULTIMA BOLACHINHA DO PACOTE!!SEM CONTAR QUE RAMIRO E JAEL MESMO NÃO JOGANDO NADA SEMPRE SÃO SEUS TITULARES!!",
            "date": "2018-11-16T09:37:36",
            "likes": "0",
            "unlikes": "0",
            "replies": [
                {
                    "name": "Paulo Morais",
                    "text": "Arrogante este Michel, chamando de \"infelicidade\" uma falha grave dele.",
                    "date": "2018-11-16T10:11:15",
                    "likes": "0",
                    "unlikes": "0"
                }
            ],
            "n_replies": 1
        },
        {
            "name": "Marcelo Gomes",
            "text": "MICHEL É UM JOGADOR INSUFICIENTE PARA A GRANDEZA DO GRÊMIO E NÃO ESTOU FALANDO SÓ PORQUÊ FEZ UM GOL CONTRA ONTEM!!!",
            "date": "2018-11-16T09:28:45",
            "likes": "0",
            "unlikes": "0",
            "replies": [],
            "n_replies": 0
        },
        {
            "name": "Edson Pastorini",
            "text": "Michel, sou teu fan. De volante, tu e' titular absoluto nesse time, mas falta de sorte nao foi. E' muito melhor dizer \"Desculpa, errei!\"",
            "date": "2018-11-16T00:14:11",
            "likes": "0",
            "unlikes": "0",
            "replies": [],
            "n_replies": 0
        },
        {
            "name": "Mestre Web",
            "text": "Michel tu sempre será um reserva mesmo",
            "date": "2018-11-16T00:59:17",
            "likes": "0",
            "unlikes": "0",
            "replies": [],
            "n_replies": 0
        },
        {
            "name": "Alvaro Farias",
            "text": "Levou azar, mas o PV também saiu errado, deveria ter dito que estava na bola",
            "date": "2018-11-16T00:15:02",
            "likes": "0",
            "unlikes": "0",
            "replies": [],
            "n_replies": 0
        }
    ],
    "exception": 0,
    "url": "https://globoesporte.globo.com/rs/futebol/times/gremio/noticia/michel-explica-gol-contra-em-empate-do-gremio-com-sao-paulo-falta-de-sorte.ghtml",
    "team": "grêmio"
}