{
    "time": "athletico-pr",
    "date": "30/11/2018 17h00",
    "title": "Flamengo x Atlético-PR: Furacão deve jogar com reservas no Maracanã; veja provável escalação.Focado na final da Sul-Americana, Atlético-PR deve repetir estratégia feita contra o Ceará. Time não terá o atacante Bergson, suspenso. Jogo é às 19h de sábado",
    "author": "GloboEsporte.com",
    "text": [
        "O Atlético-PR treinou, na tarde desta sexta-feira, de olho no Flamengo, último compromisso da equipe no Campeonato Brasileiro. A atividade comandada pelo técnico Tiago Nunes foi fechada à imprensa no Engenhão. O jogo está marcado para as 19h de sábado, no Maracanã. O duelo entre Rubro-Negros foi antecipado pela CBF.",
        "De olho na final da Sul-Americana, contra o Junior Barranquilla, o Atlético-PR deve jogar com os reservas contra o Flamengo, a exemplo do que fez diante do Ceará, no empate em 2 a 2, antes da partida contra o Fluminense.",
        "+ Tabela completa do Campeonato Brasileiro",
        "+ Zé Ivaldo, Reginaldo, Rossetto e Plata se juntam ao Atlético-PR para jogo contra o Flamengo",
        "",
        "- Para nós foi ruim ser antecipado, temos pouco tempo de recuperação. O Galo, nosso adversário direto pela vaga no G-6, teve uma semana de recuperação, assim como o Flamengo. Vamos escolher os melhores atletas que estejam em condições. Podemos buscar a vaga na pré-Libertadores pelo Brasileiro. E depois, pensar exclusivamente no jogo da Sul-Americana - disse Tiago Nunes após o jogo contra o Fluminense, na quarta-feira.",
        "+ Cartola FC: escale o seu time para a rodada #38",
        "",
        "O Atlético-PR já não depende apenas das próprias forças para terminar o G-6. O Furacão terá que vencer o Flamengo e ainda torcer para que o Atlético-MG tropece diante do Botafogo.",
        "Apesar de ter se complicado na briga pelo G-6, o Atlético-PR pode chegar à Libertadores pela Copa Sul-Americana. O título, aliás, garantiria uma vaga direta na fase de grupos. O adversário na final é o Junior Barranquilla, da Colômbia.",
        "Flamengo x Atlético-PR (38ª rodada do Campeonato Brasileiro)",
        "",
        "Mais notícias do esporte paranaense em globoesporte.com/pr"
    ],
    "comments": [
        {
            "name": "Jose Alves",
            "text": "Flamengo 8 X 0 Atlético",
            "date": "2018-11-30T18:13:41",
            "likes": "26",
            "unlikes": "61",
            "replies": [
                {
                    "name": "Carlos Silva",
                    "text": "Kkkkkkkkkk",
                    "date": "2018-11-30T18:52:26",
                    "likes": "16",
                    "unlikes": "0"
                },
                {
                    "name": "Luis Cruz",
                    "text": "O Furacão vai atropelar",
                    "date": "2018-11-30T20:15:26",
                    "likes": "19",
                    "unlikes": "9"
                },
                {
                    "name": "Carlos Souza",
                    "text": "kkkkkkkkkk",
                    "date": "2018-12-03T11:45:46",
                    "likes": "0",
                    "unlikes": "0"
                }
            ],
            "n_replies": 3
        },
        {
            "name": "Celinaldo Maranhão",
            "text": "VAI VIRA R UMA BRISA NO M,ARACA !",
            "date": "2018-12-01T13:30:55",
            "likes": "3",
            "unlikes": "2",
            "replies": [
                {
                    "name": "Tiago Fernandez",
                    "text": "AHAM vai kkkkkkkkkkkkk",
                    "date": "2018-12-02T12:30:05",
                    "likes": "2",
                    "unlikes": "0"
                }
            ],
            "n_replies": 1
        },
        {
            "name": "Rafael Silva",
            "text": "Furacão é nosso freguês. 3 x 0 Flamengo.",
            "date": "2018-12-01T00:51:00",
            "likes": "18",
            "unlikes": "34",
            "replies": [
                {
                    "name": "Arthur",
                    "text": "A gente q e fregues deles srn",
                    "date": "2018-12-01T01:22:49",
                    "likes": "14",
                    "unlikes": "1"
                },
                {
                    "name": "John Valentim",
                    "text": "cada um paga de freguês no campo do outro... esse time ai do Atl do Paraná só se garante na grama sintética.",
                    "date": "2018-12-01T03:29:01",
                    "likes": "6",
                    "unlikes": "16"
                },
                {
                    "name": "Dexter Krupp",
                    "text": "RETROSPECTO ENTRE OS DOIS TIMES (Jogos oficiais*) 20 vitórias do Flamengo 22 vitórias do Atlético-PR 13 empates Sonho de flamenguista é ganhar na baixada. Em dia de furacão, urubu não voa",
                    "date": "2018-12-01T06:19:29",
                    "likes": "17",
                    "unlikes": "5"
                },
                {
                    "name": "Sandro Stocco",
                    "text": "Flamenguista devia ter vergonha clube recebe milhões da globo e todo ano é massacrado pelo CAP em curitiba ...",
                    "date": "2018-12-01T08:13:10",
                    "likes": "11",
                    "unlikes": "7"
                },
                {
                    "name": "Wilmar Costa",
                    "text": "O Atlético PR é um Leão em casa mais fora de casa não ganha de ninguém. Acho muito por causa disso do gramado sintético.",
                    "date": "2018-12-01T12:24:27",
                    "likes": "1",
                    "unlikes": "4"
                },
                {
                    "name": "Estevon Hennemann",
                    "text": "Kkk",
                    "date": "2018-12-01T13:06:22",
                    "likes": "0",
                    "unlikes": "0"
                },
                {
                    "name": "Geraldo Gerry",
                    "text": "Vinte anos sem vencer em curitiba, e é pela grama sintética. .. kkkkk iludidos!",
                    "date": "2018-12-01T13:13:23",
                    "likes": "4",
                    "unlikes": "1"
                },
                {
                    "name": "Gustavo",
                    "text": "Esses caras falam da grama artificial, que o Atlético só ganha jogando nela, mas na verdade eles não entendem que é justamente o contrário. O time do Atlético é acostumado a jogar num terreno perfeito, sem falhas, e quando sai pra jogar nesses campos porcaria, fica em desvantagem.",
                    "date": "2018-12-01T13:31:20",
                    "likes": "4",
                    "unlikes": "0"
                },
                {
                    "name": "Ruan Lopes",
                    "text": "Ruim igual o do maracanã, onde mesmo assim foi show no Flu, o Fla esse ano foi 3 a 0 em 20 minutos, quem tem time não joga em qualquer campo, na europa muitos estadios tem o mesmo gramado da arena que pra quem entende sabe que é igual apenas deixa o jogo mais rapido, como um gramado natural e molhado, se o time for bom ja era.",
                    "date": "2018-12-01T15:52:45",
                    "likes": "2",
                    "unlikes": "0"
                },
                {
                    "name": "Ruan Lopes",
                    "text": "Desculpa, eu quiz dizer quem tem time joga em qqr campo.",
                    "date": "2018-12-01T15:54:45",
                    "likes": "1",
                    "unlikes": "0"
                },
                {
                    "name": "Tiago Fernandez",
                    "text": "GOOOOOOOOOL dos RESERVAS do ATLÉTICO kkkkkkkkkk",
                    "date": "2018-12-02T12:29:50",
                    "likes": "1",
                    "unlikes": "0"
                }
            ],
            "n_replies": 11
        },
        {
            "name": "Sidnei Santos",
            "text": "John Valentim, grama sintética né kkkkkk",
            "date": "2018-12-02T09:26:19",
            "likes": "0",
            "unlikes": "0",
            "replies": [],
            "n_replies": 0
        },
        {
            "name": "Welton Sutil",
            "text": "Com Zé Ivaldo, pode esquecer...",
            "date": "2018-11-30T18:21:30",
            "likes": "21",
            "unlikes": "15",
            "replies": [
                {
                    "name": "Augusto Neto",
                    "text": "Zé Ivaldo nãooooooo, mas o time reserva vai ganhar mole dos mulambos no campo eaburacado do Maracanã. Acha que vai dar 1*0 Furacão.",
                    "date": "2018-11-30T18:42:16",
                    "likes": "18",
                    "unlikes": "9"
                },
                {
                    "name": "José Praça",
                    "text": "Meu Deus esse cara de novo na zaga.",
                    "date": "2018-11-30T18:47:45",
                    "likes": "12",
                    "unlikes": "8"
                },
                {
                    "name": "Pedrão",
                    "text": "Zé Ivaldo não, tenha piedade de nós Jesus toma conta",
                    "date": "2018-11-30T21:19:41",
                    "likes": "10",
                    "unlikes": "3"
                },
                {
                    "name": "Geraldo Gerry",
                    "text": "Zé ivaldo só precisa de confiança, era titular com o léu pereira, e qdo saiu do time todo mundo reclamou... aconteceu mesma coisa com o TH qdo voltou.",
                    "date": "2018-12-01T13:16:35",
                    "likes": "5",
                    "unlikes": "0"
                },
                {
                    "name": "Everaldo Pinheiro",
                    "text": "Geraldo foi feliz na observação, compartilho da suas palavras.",
                    "date": "2018-12-01T14:19:15",
                    "likes": "2",
                    "unlikes": "0"
                },
                {
                    "name": "Nestor Silverston",
                    "text": "Eu acreditava no Zé Ivaldo, mas que pena, comete falhas bisonhas! Devemos a ele o o empate com o Ceará",
                    "date": "2018-12-01T14:51:33",
                    "likes": "1",
                    "unlikes": "0"
                }
            ],
            "n_replies": 6
        },
        {
            "name": "Celinaldo Maranhão",
            "text": "HOJE VAI SER MASSACRE TOTAL!",
            "date": "2018-12-01T13:30:30",
            "likes": "2",
            "unlikes": "1",
            "replies": [],
            "n_replies": 0
        },
        {
            "name": "Jurandir Cruz",
            "text": "Fato raro! Hj às 19h, será transmitido no canal do SporTV. O Atual vice do Brasileirão e vice da SulAmérica, contra o futuro vice da SulAmérica de 2018. A mais pura verdade!!!!",
            "date": "2018-12-01T07:58:39",
            "likes": "3",
            "unlikes": "10",
            "replies": [],
            "n_replies": 0
        },
        {
            "name": "Guilherme Lange",
            "text": "Nãoooo Zé Ivaldo e Wanderson juntos kkkkkkk. até engulo um dos dois, mas os dois juntos formam uma zaga horrível.",
            "date": "2018-11-30T18:37:49",
            "likes": "17",
            "unlikes": "10",
            "replies": [
                {
                    "name": "Julio Fortes",
                    "text": "O Wanderson faz qualquer zagueiro jogar mau do lado dele",
                    "date": "2018-11-30T19:44:12",
                    "likes": "1",
                    "unlikes": "1"
                },
                {
                    "name": "Getulio Keidroski",
                    "text": "dispensa do ze ivaldo pelo amor de Deus",
                    "date": "2018-11-30T19:46:53",
                    "likes": "1",
                    "unlikes": "7"
                },
                {
                    "name": "Carlos Coldibelli",
                    "text": "Li várias vezes aqui , as mesmas críticas , palavrões e ofensas ao Léo Pereira . Nada como um dia após o outro ...",
                    "date": "2018-11-30T20:16:12",
                    "likes": "17",
                    "unlikes": "0"
                },
                {
                    "name": "Jhonatam Moro",
                    "text": "Verdade Carlos",
                    "date": "2018-11-30T22:42:33",
                    "likes": "3",
                    "unlikes": "0"
                },
                {
                    "name": "Jairo",
                    "text": "Ze Ivaldo é o nome do meu tio.",
                    "date": "2018-11-30T22:44:02",
                    "likes": "1",
                    "unlikes": "1"
                },
                {
                    "name": "Robinson Alves",
                    "text": "Engole um dos dois kkkkk",
                    "date": "2018-11-30T23:49:01",
                    "likes": "6",
                    "unlikes": "1"
                }
            ],
            "n_replies": 6
        },
        {
            "name": "Comentador Franco",
            "text": "Surrar o time do cheirinho é obrigação!",
            "date": "2018-11-30T21:56:23",
            "likes": "9",
            "unlikes": "11",
            "replies": [
                {
                    "name": "Aldinei Lima",
                    "text": "surra nesse timeco q se diz grande é mais q obrigação!!",
                    "date": "2018-11-30T22:19:34",
                    "likes": "7",
                    "unlikes": "6"
                }
            ],
            "n_replies": 1
        },
        {
            "name": "Augusto Neto",
            "text": "Para ganhar da mulamba está boa a escalação.",
            "date": "2018-11-30T21:29:17",
            "likes": "9",
            "unlikes": "5",
            "replies": [],
            "n_replies": 0
        },
        {
            "name": "Thiago Xavier",
            "text": "Vice da Sul Americana 2017 4 x 0 Vice da Sul Americana 2018",
            "date": "2018-11-30T20:58:22",
            "likes": "7",
            "unlikes": "27",
            "replies": [],
            "n_replies": 0
        },
        {
            "name": "Getulio Keidroski",
            "text": "Ze Ivaldo nao deveria nem ter ir viajado... Ze ivaldo NÂOOOOOOOOOOOOOOOOOOOOOO",
            "date": "2018-11-30T19:47:27",
            "likes": "6",
            "unlikes": "15",
            "replies": [
                {
                    "name": "Carlos Coldibelli",
                    "text": "Será que o amigo não é um daqueles que criticou e até pediu a cabeça do Leo Pereira ?",
                    "date": "2018-11-30T20:18:27",
                    "likes": "15",
                    "unlikes": "2"
                }
            ],
            "n_replies": 1
        }
    ],
    "exception": 0,
    "url": "https://globoesporte.globo.com/pr/futebol/times/atletico-pr/noticia/flamengo-x-atletico-pr-furacao-deve-jogar-com-reservas-na-despedida-do-brasileiro-veja-provavel-escalacao.ghtml"
}